raster_torch/__init__.py
raster_torch/rasterize.py
raster_torch-0.0.2.dist-info/LICENSE
raster_torch-0.0.2.dist-info/METADATA
raster_torch-0.0.2.dist-info/WHEEL
raster_torch-0.0.2.dist-info/top_level.txt
raster_torch-0.0.2.dist-info/RECORD
